seawolf/__init__.py
seawolf/_ax_functions.py
seawolf/_axes.py
seawolf/test.py
seawolf-2.0.4.dist-info/METADATA
seawolf-2.0.4.dist-info/WHEEL
seawolf-2.0.4.dist-info/top_level.txt
seawolf-2.0.4.dist-info/RECORD
