Metadata-Version: 2.4
Name: seawolf
Version: 2.0.4
Summary: Tools for matplotlib plots
Author: Bayron Torres Gordillo
Author-email: torres.bayron@gmail.com
License: BSD
Platform: Windows
Platform: Linux
Platform: Solaris
Platform: Mac OS-X
Platform: Unix
Requires-Python: >=3.5
Requires-Dist: numpy
Requires-Dist: pandas
Requires-Dist: seaborn
Requires-Dist: matplotlib
Dynamic: author
Dynamic: author-email
Dynamic: description-content-type
Dynamic: license
Dynamic: platform
Dynamic: requires-dist
Dynamic: requires-python
Dynamic: summary
